{
  "login": [
    {
      "id": 1,
      "usuario": "henrique",
      "senha": "admin123"
    },
    {
      "usuario": [
        "henrique",
        "enzohenrique"
      ],
      "senha": [
        "admin123\n",
        "admin123"
      ],
      "id": 2
    }
  ],
  "cadastro": [
    {
      "id": 2,
      "usuario": "henrique",
      "senha": "admin123"
    },
    {
      "usuario": [
        "henrique",
        "enzohenrique"
      ],
      "senha": [
        "admin123\n",
        "admin123"
      ],
      "id": 3
    }
  ],
  "crud": [
    {
      "usuario": "henrique",
      "produto": "Notebook\n",
      "valor": "$ 2.000",
      "quantidade": "1",
      "id": 8
    },
    {
      "usuario": "henrique",
      "produto": "Notebook\n",
      "valor": "$ 2.500",
      "quantidade": "1",
      "id": 9
    }
  ]
}